logpy/__init__.py
logpy/logger.py
logpy/ansi/__init__.py
logpy/ansi/color.py
logpy/ansi/effect.py
logpy/log/__init__.py
logpy/log/format.py
logpy/log/level.py
log.py-0.0.1.dist-info/LICENSE
log.py-0.0.1.dist-info/METADATA
log.py-0.0.1.dist-info/WHEEL
log.py-0.0.1.dist-info/top_level.txt
log.py-0.0.1.dist-info/RECORD
