Metadata-Version: 2.1
Name: log.py
Version: 0.0.1
Summary: A basic logging library for Python.
Home-page: https://github.com/SebastiaanBij/log.py
Author: Sebastiaan Bij
License: UNKNOWN
Platform: UNKNOWN
Classifier: Programming Language :: Python :: 3
Classifier: License :: OSI Approved :: MIT License
Classifier: Operating System :: OS Independent
Classifier: Typing :: Typed
Requires-Python: >= 3.10
License-File: LICENSE
